<?xml version="1.0" encoding="utf-8"?>
<odoo>
    <data>

        <record id="view_company_form_inherit" model="ir.ui.view">
            <field name="name">view.company.form.inherit</field>
            <field name="model">res.company</field>
            <field name="inherit_id" ref="base.view_company_form"/>
            <field name="arch" type="xml">
                <xpath expr="//page[@name='general_info']" position="after">
                    <page string="Muqeem API Configuration">
                        <group>
                            <group>
                                <field name="user"/>

                            </group>
                            <group>
                                <field name="password" password="1"/>
                            </group>
                        </group>
                        <div class="o_form_label">
                            <span class="text-info">
                                للارشادات في طريقة الاشتراك:
                                <a href="https://era.net.sa/hr-muqeem" target="_blank">https://era.net.sa/hr-muqeem</a>
                            </span>
                        </div>

                    </page>
                </xpath>
            </field>
        </record>

    </data>
</odoo>